[
  {
    "id": "processed_data_6-956",
    "source_id": "956",
    "date": "2024-10-21",
    "type_origin": "reply",
    "source_question": "马斯克怎么突然支持trump了？他的大儿子变性对他的伤害这么大吗😧？",
    "content": "你这是营销号级别的信息层次，不加星球就永远处于信息链的最底层\n对于马斯克这种人，那儿子死了都无所谓的，再生十个就行了，多大点事\n把你的信息层次提高100层，只需要一句话:\n马斯克其实和民主党关系一直不佳，尤其是和拜登关系极差，而哈里斯是拜登路线的延续，所以马斯克注定和民主党翻脸\n至于为什么马斯克和拜登关系极差，又需要再提升五十层，得加钱[呲牙]",
    "domains": [
      "内容创作",
      "认知"
    ],
    "type": "方法论"
  },
  {
    "id": "processed_data_6-958",
    "source_id": "958",
    "date": "2024-10-21",
    "type_origin": "reply",
    "source_question": "如何评价B站up主“潮妈”？",
    "content": "被封了以后已经快半年没打开过b站了\n但是根据一般经验，b站就是幼儿园，你关注幼儿园的事多多少少有点弱智了[呲牙]",
    "domains": [
      "内容创作"
    ],
    "type": "事实陈述/推测预测"
  },
  {
    "id": "processed_data_6-959",
    "source_id": "959",
    "date": "2024-10-21",
    "type_origin": "reply",
    "source_question": "平常都睡得着 入睡快 但是睡前玩手机之后睡觉 脑子里都是在回味游戏短视频的内容 然后就睡不着或者入睡晚 这是为什么幻幻",
    "content": "手机的光抑制褪黑素生成",
    "domains": [
      "健康",
      "内容创作"
    ],
    "type": "思维方式"
  },
  {
    "id": "processed_data_6-960",
    "source_id": "960",
    "date": "2024-10-21",
    "type_origin": "original_post",
    "source_question": "",
    "content": "150抽3个希诺宁一个七七 什么水平[呲牙]",
    "domains": [
      "消费"
    ],
    "type": "事实陈述/推测预测"
  },
  {
    "id": "processed_data_6-961",
    "source_id": "961",
    "date": "2024-10-21",
    "type_origin": "original_post",
    "source_question": "",
    "content": "股票吃人了[惊恐][惊恐][惊恐]",
    "domains": [
      "投资"
    ],
    "type": "事实陈述/推测预测"
  },
  {
    "id": "processed_data_6-962",
    "source_id": "962",
    "date": "2024-10-20",
    "type_origin": "original_post",
    "source_question": "",
    "content": "上山下乡(温柔版)[呲牙]",
    "domains": [
      "社会观察"
    ],
    "type": "事实陈述/推测预测"
  },
  {
    "id": "processed_data_6-963",
    "source_id": "963",
    "date": "2024-10-20",
    "type_origin": "reply",
    "source_question": "哥哥分析一下这是啥原理？有点好奇",
    "content": "人类本来就有谁弱谁有理，谁会卖惨就同情谁偏见\n女人还要加上一层母爱debuff，还以为自己很有爱呢[呲牙]",
    "domains": [
      "两性",
      "价值观"
    ],
    "type": "思维方式"
  },
  {
    "id": "processed_data_6-964",
    "source_id": "964",
    "date": "2024-10-20",
    "type_origin": "original_post",
    "source_question": "",
    "content": "学点江浙沪智慧[呲牙]",
    "domains": [
      "搞钱",
      "认知"
    ],
    "type": "思维方式"
  },
  {
    "id": "processed_data_6-965",
    "source_id": "965",
    "date": "2024-10-20",
    "type_origin": "reply",
    "source_question": "哥，真心求问，董yh长那样也有那么多中年梦女是怎么一回事？女人不看脸吗？",
    "content": "他半夜的是儿子或者女婿的角色\n你去相亲你妈不就给你找这样的?[呲牙]",
    "domains": [
      "两性"
    ],
    "type": "事实陈述/推测预测"
  },
  {
    "id": "processed_data_6-966",
    "source_id": "966",
    "date": "2024-10-20",
    "type_origin": "original_post",
    "source_question": "",
    "content": "老实说杨立编的段子只看文字的话，攻击性并不是很强，没有哥哥的百分之一\n关键还是在于她那张脸，和段子一配合就超恶心了\n全网哥哥应该是第一个发现本质的，同样的段子要是随便换个美女来讲，那评价恐怕会变成挺中肯的，没毛病[呲牙]",
    "domains": [
      "内容创作",
      "两性",
      "认知"
    ],
    "type": "方法论"
  },
  {
    "id": "processed_data_6-967",
    "source_id": "967",
    "date": "2024-10-20",
    "type_origin": "reply",
    "source_question": "哥，北京某211大三，现在准备混个毕业证考本校研究生跟着我导师做ai＋碳中和，现在论文发了好几篇了，但是不想去上课，我手里有重度抑郁证明，教教我如何一节课都不上可以吗，我比较笨 能说的详细点吗",
    "content": "我其实不太懂 上课不就是坐后排玩电脑吗 这都不愿意 还是说现在不能这么干了 问你问题你就说不会呗[呲牙]",
    "domains": [
      "教育",
      "学习",
      "价值观"
    ],
    "type": "思维方式"
  },
  {
    "id": "processed_data_6-968",
    "source_id": "968",
    "date": "2024-10-20",
    "type_origin": "reply",
    "source_question": "幻大，湖南双非一本法学大三废物女，卷不过同学没有保研资格，家在内陆三线城市小康水平，父母亲戚均是tz内。现在焦虑得整宿失眠，考研法硕众所周知卷的飞起还有推免居多、统考缩招、学制延长的大趋势，由于书读得晚本科毕业就24了，冲92硕或者家里蹲考公心理压力太大，想转行去做外贸或出海相关的又担心war风险学徒还没上手就寄了，大城市打工有没有什么好点的行业、公司未来能苟住啊，普通人只知道宠物行业、银发养老、情绪经济这些大词。星球问答高强度刷了一阵好像没看到这些贴，您往期的付费专栏和自媒体课都买了，求幻大指教",
    "content": "1 你可以出去水个硕博 当然现在东南亚已经不行了 最好去欧洲\n欧洲很多免费或者低收费项目，具体我不太清楚，但是刷到过\n然后在回国进体制 保那个研不是找事嘛\n2 这个倒确实是个问题 现在打工其实没有什么出路了 普通人还在往打工方向努力基本上就浪费时间了\n其实现在对于00后来说，都是副业为王，副业挣得比主业还多了\n哥哥算是最早一批副业大于主业，最后副业变成主业的\n小红书上闲鱼上，这种干副业的也很多，你可以观察一下，有空了以后再提一嘴，现在没空",
    "domains": [
      "教育",
      "职业",
      "搞钱"
    ],
    "type": "方法论"
  },
  {
    "id": "processed_data_6-969",
    "source_id": "969",
    "date": "2024-10-20",
    "type_origin": "original_post",
    "source_question": "",
    "content": "最近才了解 \n好处费具体是五六万美元一个 八九十年代就这个价噢 当年靠这挣外汇呢\n然后绝大多数 90%以上都被🇺🇸白鬼收养了\n而且带走还不一定是健康小孩，很多都是残疾的痴呆的弱智的，但是🇺🇸白鬼不管这些，全都要，爱心泛滥了[呲牙]",
    "domains": [
      "社会观察"
    ],
    "type": "事实陈述/推测预测"
  },
  {
    "id": "processed_data_6-970",
    "source_id": "970",
    "date": "2024-10-20",
    "type_origin": "reply",
    "source_question": "哥哥，刷到个九价的评论如下:\n2价很划算，但对身体也有影响，9价打完导致内壁营养层变薄很多，自然月经就少了，而且不易怀孕，即使怀孕也容易流产，要是生下来了，畸形率提高三四倍，而且会遗传，这是上海那边医院测出来的，后来新闻被压下去了[笑哭R]\n\n哥哥，这样的各种新💉，是不是跟冠💉，不论国产进口，只要不是快嗝屁要救命的都别碰。\n\n像维生素这种发现了快百年的，并且国外进口一直用的，才会好一点，国💊也不行\n\n求科普",
    "content": "有家族病史可以打 没有折腾个🐔",
    "domains": [
      "健康"
    ],
    "type": "方法论"
  },
  {
    "id": "processed_data_6-971",
    "source_id": "971",
    "date": "2024-10-19",
    "type_origin": "reply",
    "source_question": "哥 经常叹气怎么办，有的时候感觉胸口堵得慌，叹一口气才舒服。",
    "content": "医院看看 拍个片",
    "domains": [
      "健康"
    ],
    "type": "方法论"
  },
  {
    "id": "processed_data_6-972",
    "source_id": "972",
    "date": "2024-10-19",
    "type_origin": "reply",
    "source_question": "好哥哥你站那一边啊哈哈哈",
    "content": "大学生就喜欢整这些没有用的东西浪费生命 出来就只能去奶茶店摇奶茶 或者做🐔骗彩礼\n懂事的大学生做好两个字就行了[呲牙]",
    "domains": [
      "教育",
      "两性"
    ],
    "type": "思维方式"
  },
  {
    "id": "processed_data_6-973",
    "source_id": "973",
    "date": "2024-10-19",
    "type_origin": "reply",
    "source_question": "被失眠整麻了哥。。能推下之前说的助眠产品吗",
    "content": "试了一段时间 还可以",
    "domains": [
      "健康",
      "情绪"
    ],
    "type": "事实陈述/推测预测"
  },
  {
    "id": "processed_data_6-974",
    "source_id": "974",
    "date": "2024-10-19",
    "type_origin": "reply",
    "source_question": "哥哥，因为我想进超一线城市的初中，当英语教师，找关系混进去，所以打算跨考翻硕，请问英语口语听力怎么一年内快速提高",
    "content": "一年再怎么样肯定也够了 我觉得只要坚持\n方法网上很多吧 其实方法真的没有坚持重要",
    "domains": [
      "学习"
    ],
    "type": "方法论"
  },
  {
    "id": "processed_data_6-975",
    "source_id": "975",
    "date": "2024-10-19",
    "type_origin": "original_post",
    "source_question": "",
    "content": "小逼仔准备学以致用了[呲牙]",
    "domains": [
      "教育"
    ],
    "type": "思维方式"
  },
  {
    "id": "processed_data_6-976",
    "source_id": "976",
    "date": "2024-10-19",
    "type_origin": "reply",
    "source_question": "爹，我是之前问高中教师择校的，能讲讲为什么去二三档就毁了吗？名气大平台高市场不会更好吗？",
    "content": "你去全省最好的学校 接触的也是全省最牛逼的家长和学生\n你去上海的二三档学校 接触的是二三档的家长和学生\n这些人有个🐔巴实力，绝大多数说白了就是早年祖上留下两三套房，莫名其妙就躺赢了，卡里面可能就二三十万，小市民一个",
    "domains": [
      "教育"
    ],
    "type": "思维方式"
  }
]
