[
  {
    "id": "processed_data_7-2056",
    "source_id": "2056",
    "date": "2024-08-04",
    "type_origin": "original_post",
    "source_question": "",
    "content": "今年报志愿 哥哥就墙裂推荐精神医学这个专业\n精神病院以前都是关那种得罪领导的、进京告状的少数fifa人员\n现在是万物皆可精神病了，是不是精神病，决定权已经下放到派出所晶哥手里，说你是你就是了，可见这个专业前途不可限量啊[呲牙]",
    "domains": [
      "教育",
      "职业"
    ],
    "type": "事实陈述/推测预测"
  },
  {
    "id": "processed_data_7-2057",
    "source_id": "2057",
    "date": "2024-08-04",
    "type_origin": "original_post",
    "source_question": "",
    "content": "哥哥有粉丝把老头打了一顿\n结果老头报🚓，晶哥直接给送精神病院了，我让他赶紧给老头认怂，这才放出来\n这是什么操作，现在都这么耍的了？不应该调解调解和稀泥吗？\n只能说越来越会耍了，幸好咱生得早啊，可以随便打[呲牙]",
    "domains": [
      "人际"
    ],
    "type": "事实陈述/推测预测"
  },
  {
    "id": "processed_data_7-2058",
    "source_id": "2058",
    "date": "2024-08-04",
    "type_origin": "original_post",
    "source_question": "",
    "content": "卖猪下水?[呲牙]",
    "domains": [
      "搞钱"
    ],
    "type": "事实陈述/推测预测"
  },
  {
    "id": "processed_data_7-2060",
    "source_id": "2060",
    "date": "2024-08-03",
    "type_origin": "original_post",
    "source_question": "",
    "content": "年轻人四条出路，那个是开玩笑的同志们\n现在千万不能悲观了，希望就在前方\n去年在金三角的时候就说了，赶英超美超英赶美\n都按着剧本来的，急什么，现在还是继续卷吧[呲牙]",
    "domains": [
      "社会观察"
    ],
    "type": "事实陈述/推测预测"
  },
  {
    "id": "processed_data_7-2061",
    "source_id": "2061",
    "date": "2024-08-03",
    "type_origin": "reply",
    "source_question": "坐标武汉985，学长分享实习经验，拼多多实习，一堆华五的，要求每天11点干到23点，学长说每天晚上回家直接摊掉只能刷手机，干几年后身体报废滚蛋回老家。\n\n学历这条路已经彻底完蛋了，以后真的硕士毕业卖炸鸡了😭😭😭",
    "content": "哥哥直播时介绍过四条出路 可没有说过卷学历呢[呲牙]",
    "domains": [
      "教育",
      "职业",
      "健康"
    ],
    "type": "事实陈述/推测预测"
  },
  {
    "id": "processed_data_7-2062",
    "source_id": "2062",
    "date": "2024-08-03",
    "type_origin": "reply",
    "source_question": "幻 这下是不是要逐步上线实名上网了🥺",
    "content": "关我屁事 明年哥哥就撤了[呲牙]",
    "domains": [
      "社会观察"
    ],
    "type": "事实陈述/推测预测"
  },
  {
    "id": "processed_data_7-2063",
    "source_id": "2063",
    "date": "2024-08-03",
    "type_origin": "reply",
    "source_question": "幻哥，俺在某985学人工智能专业，当前大四暑假，在某聘某猎等软件查看工作要求后发现大多数人工智能岗位要求硕士学历，遂当前计划是考本校研，想问人工智能哪些细分领域比较好。（俺也知道学这个专业该润嘞，但是家里条件不算好润不出去，计划工作后攒几年米再润）\n1、NLP（自然语言处理）：当下热门的大语言模型就是这个领域的，而且在校期间跟着导师做过nlp项目，对该领域比较熟悉，从lstm到nltk、transformers都会用点。但是很难说硕士毕业后前景如何。\n2、CV（计算机视觉）：主要分为图像处理和图像生成，图像生成的典型应用就是ai绘画，火过一阵了已经，图像处理比较典型的应用就是目标识别、人脸识别之类的。当前依旧处于发展阶段，但是研究成果没有大语言模型这么通用，往往只用于解决某一个或某一类垂直细分领域的问题。\n3、嵌入式开发。这个了解不是很多，但是好处是和幻之前说的自动驾驶、自动化等技术相关，但是由于涉及到硬件，自学较困难（自学嵌入式的话很多硬件设施价格较高）\n4、诸如计算实验、数据处理、量化交易等其他领域。\n求幻哥帮忙看看，感激不尽！",
    "content": "穷人当然先弄学了马上能赚钱能吃饭的 别的以后再说\n所以要求就是快点毕业快点找工作快点赚钱 如果nlp符合的话那就先学着吧 别的以后再说呗",
    "domains": [
      "教育",
      "职业",
      "搞钱"
    ],
    "type": "方法论"
  },
  {
    "id": "processed_data_7-2064",
    "source_id": "2064",
    "date": "2024-08-03",
    "type_origin": "reply",
    "source_question": "幻，建筑土木大类的专业直接找工作是不是比读研性价比高啊？",
    "content": "那是当然",
    "domains": [
      "教育",
      "职业",
      "决策"
    ],
    "type": "事实陈述/推测预测"
  },
  {
    "id": "processed_data_7-2065",
    "source_id": "2065",
    "date": "2024-08-03",
    "type_origin": "original_post",
    "source_question": "",
    "content": "我感觉吧 学历高的男大都应该少打✈️多捐晶\n一个是可以多卖钱 你打✈️一分钱都捞不着 但是捐晶几千到几万不等\n一个是可以给自己留后，莫名其妙多很多儿子女儿，以后可以慢慢相认嘛\n爽啊，之前没想明白呢，以后要多捐了，有事没事就捐一发[呲牙]",
    "domains": [
      "两性",
      "健康",
      "搞钱"
    ],
    "type": "方法论"
  },
  {
    "id": "processed_data_7-2066",
    "source_id": "2066",
    "date": "2024-08-03",
    "type_origin": "reply",
    "source_question": "幻，数理逻辑不强，智力不高，除了文科，医学学什么类型的专业有前途",
    "content": "学电焊",
    "domains": [
      "教育",
      "职业",
      "搞钱"
    ],
    "type": "方法论"
  },
  {
    "id": "processed_data_7-2067",
    "source_id": "2067",
    "date": "2024-08-03",
    "type_origin": "reply",
    "source_question": "哥，大学生有啥推荐的书，看那些治国理政的书有用吗",
    "content": "说什么呢一天天的[呲牙]",
    "domains": [
      "学习",
      "教育"
    ],
    "type": "事实陈述/推测预测"
  },
  {
    "id": "processed_data_7-2068",
    "source_id": "2068",
    "date": "2024-08-03",
    "type_origin": "reply",
    "source_question": "幻哥，我妈有神经病，大多数状态挺好的，隔几年会发病一次住院，她特别信她的兄弟姐妹，把钱都放他弟弟那，就是一些低保钱卖庄稼的钱，这些是明确我妈自己支配的，我爸也会把一些现金放在抽屉里随便拿，我妈只会在用的时候拿几张。我爸不知道低保有多少钱，他以为一年五六千，但实际是一万到两万（现在知道）我妈平时也不怎么买东西。我记得我小时候就是家里有大事需要钱就从舅舅家拿，她这几个兄弟姐妹都不怎么样，我那个舅算是最明事理的（表面上），姥爷家拆迁，在农村大部分都是归儿子，女儿没有，但是我姨家有分到钱，就我妈什么都没有，姥爷姥姥去世的时候分东西，别人分到什么我不知道，但我妈就几床破棉被烂木床。这些我爸心里门清，他不想计较。我妈坚信全是我舅的，姨一点没有（治疗费啥的我家应该没出钱）\n去年我妈住院，发生什么事情我没印象了，就开始算钱，我姐就想把放在舅舅那的钱拿回来，具体有多少不知道，但舅家有个小本记着，当时问我爸同不同意，他也不吭声不表态。就一直跟舅要，一开始说有个七八万后来又说有个九万十万，一直找各种理由不给钱，后来又说过完年就给，当时临近过年，我跟我姐都信了。当时都串亲戚嘛，舅来我家，说我姐想要把钱拿回来怎么怎么的，我爸还是不表态。之后跟我姐说不要要钱了，我姐就问为什么，他就说我姐什么都不懂。也不知道出于什么理由，舅把这事告诉姨的儿子了，儿子又跟他妈说了。姨就来我家，不是特地来的，跟我爸说不要给女儿钱，我姐想要那个钱就是自己独吞。当时已经过去一个月半个月了，我爸以为早就没要钱了，就跟我姐吵，说“要把这点亲戚情分消磨没了，你就算一直要，这个钱也是给我给不到你”之后这件事就不了了之。我姐明确跟我表态说要回来这个钱，直接存我妈名下，存个定期，谁也不动这笔钱。一开始不知道有近十万，我家也不是什么大富大贵，我爸就一工地搬砖的，十万本身就不是小数目，一年的利息也不少\n我到现在也还是不明白其中有什么人情世故所谓亲戚情分，我姨又有什么利益立场站在舅那边，这笔钱又给不到他一点",
    "content": "都这么穷了 还分析啥呢 累不累 穷人本来就智商低了 还分析个什么劲",
    "domains": [
      "认知"
    ],
    "type": "故事案例"
  },
  {
    "id": "processed_data_7-2069",
    "source_id": "2069",
    "date": "2024-08-03",
    "type_origin": "reply",
    "source_question": "哥哥，你看我的思路正确吗？以前鼻炎开药被一个老登坑了1000，还不是老东西硬拉着我去的，现在一想到就头疼恶心，所以我现在很讨厌别人挣我钱啊\n以前打算把钱花完找暑假工，然后我发现与其辛辛苦苦做廉价劳动力挣钱，完全不如想方设法把钱省下来，躺平玩手机都比打工好\n以后想办法多挣钱咯，不行的话就都自己做饭，不买车，不出彩礼，保证健康，坚决避免医疗消费……\n有的人辛辛苦苦做牛马也挣不了几个钱，而那些拥有资产的人挣钱却很轻松，买东西我只用pdd，购买廉价的农民工人的商品不好吗\n我爸在东莞的厂里做厨师，我可以住，暑假每天坐公交地铁到深圳玩，除了交通不花钱\n我还可以在东莞深圳闲鱼淘点二手货，一切皆可二手\n目前打算发展做饭的爱好，不可能在外面吃饭的，便宜和健康不可兼得\n把颜值弄好，想办法白嫖，应该比挣钱嫖简单\n还有研究一下保险，把老东西的钱省下来\n我现在感觉读书啃老是真舒服",
    "content": "省钱总是对的",
    "domains": [
      "消费",
      "搞钱",
      "职业"
    ],
    "type": "思维方式"
  },
  {
    "id": "processed_data_7-2070",
    "source_id": "2070",
    "date": "2024-08-03",
    "type_origin": "original_post",
    "source_question": "",
    "content": "感觉有点亏啊，少拿了几百万呢，哥哥也应该这么耍的[呲牙]",
    "domains": [
      "搞钱"
    ],
    "type": "事实陈述/推测预测"
  },
  {
    "id": "processed_data_7-2071",
    "source_id": "2071",
    "date": "2024-08-02",
    "type_origin": "original_post",
    "source_question": "",
    "content": "忍不住还是把避孕套的事情告诉老东西了，果然又是经典无视[呲牙]",
    "domains": [
      "两性",
      "人际"
    ],
    "type": "事实陈述/推测预测"
  },
  {
    "id": "processed_data_7-2072",
    "source_id": "2072",
    "date": "2024-08-02",
    "type_origin": "reply",
    "source_question": "哥哥俺们臭文科怎么办啊😭😭😭",
    "content": "直播说过很多次了\n学语言 学技术 尼给路[呲牙]",
    "domains": [
      "学习",
      "教育",
      "职业"
    ],
    "type": "事实陈述/推测预测"
  },
  {
    "id": "processed_data_7-2073",
    "source_id": "2073",
    "date": "2024-08-02",
    "type_origin": "original_post",
    "source_question": "",
    "content": "老东西已经疯魔了，在想该不该把避孕套的故事告诉她[呲牙]",
    "domains": [
      "两性",
      "人际"
    ],
    "type": "事实陈述/推测预测"
  },
  {
    "id": "processed_data_7-2074",
    "source_id": "2074",
    "date": "2024-08-02",
    "type_origin": "original_post",
    "source_question": "",
    "content": "到底是进体制还是搞钱，哥哥当年权衡过太多次了\n但是不管怎么权衡，搞钱都更有性价比\n哥哥经常遇到些惋惜哥哥为什么不进体制的，哥哥都是当笑话看，还活在老版本呢[呲牙]",
    "domains": [
      "职业",
      "搞钱",
      "决策"
    ],
    "type": "价值观"
  },
  {
    "id": "processed_data_7-2075",
    "source_id": "2075",
    "date": "2024-08-02",
    "type_origin": "original_post",
    "source_question": "",
    "content": "看到没有，一个处级干部就能把清华本硕被拷打成这样 哥哥早看明白了 整天想着靠学历就能升官 有你份吗？[呲牙]//: 有没有人看出姜桂芳明明有能力责任心强，却被单位里绝大多数人讨厌，最后被投票开除的底层逻辑?\n我看看有没有人能说明白，说不明白你以后大概也是要坐冷板凳的，要是都没人能说明白，我就提一嘴[呲牙]",
    "domains": [
      "职业",
      "教育"
    ],
    "type": "事实陈述/推测预测"
  },
  {
    "id": "processed_data_7-2076",
    "source_id": "2076",
    "date": "2024-08-02",
    "type_origin": "original_post",
    "source_question": "",
    "content": "代孕这一块哥哥刚开始研究 感觉水很深啊 价格不算透明\n等什么时候琢磨明白了 又可以像拉皮条一样 开个账号给大家服务了 这个比拉皮条安全[呲牙]",
    "domains": [
      "两性",
      "搞钱",
      "消费"
    ],
    "type": "事实陈述/推测预测"
  }
]
