[
  {
    "id": "processed_data_7-2117",
    "source_id": "2117",
    "date": "2024-07-30",
    "type_origin": "reply",
    "source_question": "幻哥，现在普通人有没有必要囤积物资以防范未来社会发生脆断的危险？（顺带倒买倒卖）",
    "content": "现在要做的事 说过很多次了[呲牙]",
    "domains": [
      "搞钱"
    ],
    "type": "事实陈述/推测预测"
  },
  {
    "id": "processed_data_7-2118",
    "source_id": "2118",
    "date": "2024-07-30",
    "type_origin": "reply",
    "source_question": "贴吧考古，泪目了，时代的眼泪，创业七年了",
    "content": "哪里创业了。整天混吃等死[呲牙]",
    "domains": [
      "搞钱"
    ],
    "type": "事实陈述/推测预测"
  },
  {
    "id": "processed_data_7-2119",
    "source_id": "2119",
    "date": "2024-07-30",
    "type_origin": "original_post",
    "source_question": "",
    "content": "有点巩布了[呲牙]",
    "domains": [
      "情绪"
    ],
    "type": "事实陈述/推测预测"
  },
  {
    "id": "processed_data_7-2120",
    "source_id": "2120",
    "date": "2024-07-30",
    "type_origin": "reply",
    "source_question": "幻哥，发达国家已经经历的是发展中国家正在经历的吗？",
    "content": "错误的 大多数穷国生生世世都是穷国 大多数学渣这辈子都是学渣 学霸经历过学渣经历过的东西吗",
    "domains": [
      "教育"
    ],
    "type": "思维方式"
  },
  {
    "id": "processed_data_7-2121",
    "source_id": "2121",
    "date": "2024-07-30",
    "type_origin": "reply",
    "source_question": "幻，刚刚有人用邮箱给我发了个文件里面写着个人综测明细，还附上了链接，我第一遍看完就觉得办公室前缀不标学校名称、强调加密文件、退出无法查看、模糊表格这些都有问题，但是因为我放暑假了之后就没想起要去看期末的考试成绩，还以为出了什么问题就很急切地去点看来看。明明意识到有问题但还是去做了，心里的急切压制住了感觉不对劲的感觉，差点就被盗号了，类似骗别人ta家人出事了住院让打钱那种？之前幻幻说过会被骗是因为贪，那这种情况该怎么办……？还是说“急切地想要知道结果、解决问题”本身就是一种贪？",
    "content": "综测是什么垃圾 评分高是不是分配2万一个月的工作[呲牙]",
    "domains": [
      "教育",
      "职业",
      "人际"
    ],
    "type": "方法论"
  },
  {
    "id": "processed_data_7-2122",
    "source_id": "2122",
    "date": "2024-07-30",
    "type_origin": "reply",
    "source_question": "以前冲动消费 买的各种洛丽塔 jk 化妆品 在游戏里猛猛氪金 过段时间发现自己根本不喜欢了 在闲鱼上卖也是大亏 不卖更是烂在手里 后悔死了哥",
    "content": "去拍擦边视频回本[呲牙]",
    "domains": [
      "内容创作",
      "搞钱",
      "消费"
    ],
    "type": "事实陈述/推测预测"
  },
  {
    "id": "processed_data_7-2123",
    "source_id": "2123",
    "date": "2024-07-30",
    "type_origin": "reply",
    "source_question": "幻哥 今年17岁女高 bmi21.2 你说这个16/8轻断食（不吃早餐）适合我吗🧐",
    "content": "试试看呗",
    "domains": [
      "健康"
    ],
    "type": "事实陈述/推测预测"
  },
  {
    "id": "processed_data_7-2124",
    "source_id": "2124",
    "date": "2024-07-30",
    "type_origin": "original_post",
    "source_question": "",
    "content": "⏰味拉满的两个人，从出生地到长相到经历，都是满满的⏰味[呲牙]",
    "domains": [
      "社会观察"
    ],
    "type": "事实陈述/推测预测"
  },
  {
    "id": "processed_data_7-2125",
    "source_id": "2125",
    "date": "2024-07-29",
    "type_origin": "original_post",
    "source_question": "",
    "content": "经过深入交流后 哥哥搞清楚真相了\n图是假的 真人就那样 颜值打四折吧 但是故事都是真的[呲牙]//: 艹是盗图 被骗了 幸好没被爆金币[呲牙]",
    "domains": [
      "人际"
    ],
    "type": "事实陈述/推测预测"
  },
  {
    "id": "processed_data_7-2126",
    "source_id": "2126",
    "date": "2024-07-29",
    "type_origin": "reply",
    "source_question": "幻大求指点，我今年高三刚毕业，高中三年主动和班里的同学保持距离，认识的几个人也挺牛马，和原来的朋友讲不到一块去，渐行渐远。困在这种环境里感觉深受其害，有什么办法能和新的人接触？在过去的有不太愉快的人际交往的经历，怎么摆脱消极观念？",
    "content": "结交网友 soul上面发张照片 就可以开始了",
    "domains": [
      "人际"
    ],
    "type": "事实陈述/推测预测"
  },
  {
    "id": "processed_data_7-2127",
    "source_id": "2127",
    "date": "2024-07-29",
    "type_origin": "reply",
    "source_question": "哥哥 我发现我咋总忘事呢 经常要干啥前脚记得后面直接忘记要干啥 然后吧 我每次要两件事以上都得拿手机记一下 不然肯定记不全",
    "content": "买点维生素片补一补",
    "domains": [
      "健康"
    ],
    "type": "事实陈述/推测预测"
  },
  {
    "id": "processed_data_7-2128",
    "source_id": "2128",
    "date": "2024-07-29",
    "type_origin": "original_post",
    "source_question": "",
    "content": "已经有人发现了 喜欢无差别献忠的，都是五六十岁的老东西[呲牙]",
    "domains": [
      "社会观察"
    ],
    "type": "事实陈述/推测预测"
  },
  {
    "id": "processed_data_7-2129",
    "source_id": "2129",
    "date": "2024-07-29",
    "type_origin": "reply",
    "source_question": "想问问幻哥\n为什么我觉得买什么东西之前都要去学习一遍，才能尽量的防止被坑，要不然就是装做看起来很不好惹，还是说生意就该这么做\n我遇到的事情：\n1.去买菜或者买花，人家看我年轻或者不常来就会坑我\n\n2.找健身私教，因为我平时不怎么用美团，那些人会告诉我一个较高的价格，有时候也不知道大概价钱，所以还是被坑了点，\n后面他们故意不给你好好弄，然后等到差不多结束的时候告诉你还需要再买点巩固一下，很多问题我也搞不明白，去网上搜，说什么的都有\n\n3.去租房，要先查各种攻略，住了之后发现房东可能坑你水电钱，\n或者因为没经验，尽管上网搜了还是会有扯皮的时候\n或者中介利用各种方式骗钱，但是又是小钱，没必要打官司\n\n4.然后我在网上看到有些几千块钱快递丢了只配3块钱，一定要明白什么法律，告诉客服才能得到赔偿\n\n5.我现在虽然买不起房子哈，但是我知道装房子的时候那些师傅不给你好好整，故意骗你说这好，实际上想偷懒\n\n6.打工时候扣工资什么的各种操作不用说了\n这个好像不限于国内，我看一些博主在国外租房啊，或者打工什么的也是这样的\n\n问题：\n1.难道做生意一定要这样吗，这种算计应该有一个什么样的程度才是最好的呢\n2.如果说要去买什么的时候，要提前了解，并且要凶一点吗，但是每次都这样真的很累",
    "content": "只有在文明古国做生意，或者说和文明古国的人做生意，才会这样\n比如埃及、印度、伊拉克、伊朗、越南啥的\n如果你跟非文明古国的人打交道，被坑的概率就会急剧降低\n非文明古国的人都比较傻，做事情没什么套路，该怎么样就怎么样\n文明古国的人喜欢互坑互害，所以如果你发现好像很优惠的样子，那就要打起十二万分精神了\n\n解决办法其实也是有的，就是依赖网络，非必要尽量不做线下交易，能线上就绝不线下\n比如说像吃饭我就避免不了\n但是比如打车我只用滴滴，出租车司机说的再天花乱坠我都不信，这样就能极大避免被坑的风险\n包括卖课，我也只做线上，从不线下，但凡要是动了一点线下的念头，前几年那波都够我喝一壶的，这就是线上的好处\n简单来说就是我知道你肯定是坏种，你肯定会坑我，所以需要隔一条网线降低风险，线上走平台本质上是让平台帮你分散风险",
    "domains": [
      "搞钱",
      "决策",
      "职业"
    ],
    "type": "方法论"
  },
  {
    "id": "processed_data_7-2130",
    "source_id": "2130",
    "date": "2024-07-29",
    "type_origin": "reply",
    "source_question": "身价指的是啥",
    "content": "就是把身上之前的东西都加起来 看看值多少钱 其实很虚",
    "domains": [
      "搞钱"
    ],
    "type": "思维方式"
  },
  {
    "id": "processed_data_7-2131",
    "source_id": "2131",
    "date": "2024-07-29",
    "type_origin": "original_post",
    "source_question": "",
    "content": "学着点你们这帮废物[呲牙]",
    "domains": [
      "情绪"
    ],
    "type": "事实陈述/推测预测"
  },
  {
    "id": "processed_data_7-2132",
    "source_id": "2132",
    "date": "2024-07-29",
    "type_origin": "original_post",
    "source_question": "",
    "content": "有人说哥哥居然会说心疼宝宝这种话，说明哥哥过于渴批了\n能得出这结论只能说明你幼稚了\n因为情绪价值也是价值的一种，情绪价值多给一点，钱不就可以少花一点\n这么简单的道理，没有哥哥开示你怕是永远都不会明白了，缺少慧根呢[呲牙]",
    "domains": [
      "两性",
      "价值观"
    ],
    "type": "思维方式"
  },
  {
    "id": "processed_data_7-2133",
    "source_id": "2133",
    "date": "2024-07-29",
    "type_origin": "reply",
    "source_question": "幻哥～听你的话已经开始老实做自媒体了，拍了一段时间，总感觉找不到适合的方向，\n\n问题：本来是想往母婴赛道发展的，但是感觉我的拍摄风格更吸引男生，但是男粉又不好转化。拍日常感觉流量还行，一拍涉及育儿类的流量就不行了。\n\n想问问幻哥的建议555，哥哥觉得我这种感觉的可以更多的尝试一下啥赛道呀？「已报课」\n\n账号：1388695591",
    "content": "首先是视频本身就不行 \n你这个太磨叽了 现在都追求短平快 赶紧说重点呢\n看看那些美妆博主 都是一句话一个镜头的 一个是快 一个是不停地变来变去 观众不会无聊\n开头就不行 大学生就业指南有什么屁用 你应该直接说一个月挣多少 工作多轻松之类的 重点放前头 然后再往下讲\n语速也是平时说话的语速和调调 这在自媒体这一块不行 你看我拍视频什么语速什么调调 我现实中也不这么说话啊\n不管你做什么赛道 都应该认真把这一块所有大V的视频都刷一遍 好好学习 先从模仿别人风格做起 你这一看就是没认真研究别人自己就上手了 太急\n赛道其实不重要 如果你吸男粉那这个号就开直播骗礼物了，做别的另外开个号就行了",
    "domains": [
      "内容创作",
      "搞钱",
      "职业"
    ],
    "type": "方法论"
  },
  {
    "id": "processed_data_7-2134",
    "source_id": "2134",
    "date": "2024-07-29",
    "type_origin": "original_post",
    "source_question": "",
    "content": "艹是盗图 被骗了 幸好没被爆金币[呲牙]",
    "domains": [
      "人际"
    ],
    "type": "事实陈述/推测预测"
  },
  {
    "id": "processed_data_7-2135",
    "source_id": "2135",
    "date": "2024-07-29",
    "type_origin": "original_post",
    "source_question": "",
    "content": "穷蛆们羡慕吗？[呲牙]",
    "domains": [
      "情绪"
    ],
    "type": "事实陈述/推测预测"
  },
  {
    "id": "processed_data_7-2136",
    "source_id": "2136",
    "date": "2024-07-29",
    "type_origin": "original_post",
    "source_question": "",
    "content": "啊这种女生没有男人舔着和养着吗\n\n这是个好问题\n答案是脾气不好，原生家庭不好，有抑郁症，喜欢冲男人耍性子，只和她短期玩玩[呲牙]",
    "domains": [
      "两性"
    ],
    "type": "事实陈述/推测预测"
  }
]
