[
  {
    "id": "processed_data_7-1602",
    "source_id": "1602",
    "date": "2024-09-06",
    "type_origin": "reply",
    "source_question": "幻哥，高三读不下去了昨办？！\n我想远离普高，远离父母，远离这个县城。\n能出国不？上大专也行。\n我就是想立刻从高考这个敌人面前逃走啊，其实换个地方我不一定混得好，\n而家人也很难同意。我家在浙江一个县城，我是独生女，我不清楚家里有多少钱，有2套恒大的房，2套老小区的房，3套近郊的房，一辆奔驰450l，一辆宝马x1。给嗲嗲治病，准备花一百万，房车无恙，看来有点存款。父母到了中年危机，事业走下坡路，如今死咬一份工作而已。\n我初一认识幻哥，此后在厌学与刷题中来回切换。现在我厌学持续半年了，是最久的一次，成绩从500分降到430。\n题目并不可憎，可我为什么讨厌在学校学习呢。\n我还不想自刎，我还想用活着这件事换点东西，比如让父母掏钱助我去享乐\n我想做的事从来没实现过，以后也如此吧，留学和自杀都不会成真。\n我在高考这口锅里翻涌，身心都被煮烂，直到铃声响起，高考结束了，我被掖进一张巨口。\n幻哥，高三读不下报去昨办？求给点建议！\n谢谢幻哥",
    "content": "你要不试试自学 你是不是被学校压迫惨了才这样的 你搞不好只是讨厌学校而已\n或者可以用会考成绩申请留学 欧美要求高 去马来西亚或者泰国还是可以的\n或者去香港读专升本 那也不错",
    "domains": [
      "教育",
      "职业",
      "决策"
    ],
    "type": "方法论"
  },
  {
    "id": "processed_data_7-1603",
    "source_id": "1603",
    "date": "2024-09-06",
    "type_origin": "original_post",
    "source_question": "",
    "content": "昨天用力过猛，给干尿了两次\n搞得地板上还有淡淡的尿骚味，害我还得擦地板，讨厌[发怒]",
    "domains": [
      "健康",
      "情绪"
    ],
    "type": "事实陈述/推测预测"
  },
  {
    "id": "processed_data_7-1604",
    "source_id": "1604",
    "date": "2024-09-06",
    "type_origin": "reply",
    "source_question": "哥哥，女生怎么解决生理需求\n\n最近整天都很烦躁，总感觉有什么要发泄，甚至影响到做事。试过运动和diy，还是不行，就想要鲜活的荷尔蒙接触\n本人素颜清纯小美女，偏向白幼瘦，日常穿搭比较休闲幼稚，但胸真的很小，显身材的衣服也撑不起来。主动加我的大多数是竹竿男，偏偏我喜欢高个宽肩健身肌肉阳刚男，但那种好像普遍喜欢胸大的微胖mm，或者时尚潮女，感觉无望\n\n我现在就想单纯解决生理需求，亲嘴拥抱（但不做，没做过也不喜欢纳入）。有时候路上看到一个肌肉男就想亲一个，只想亲不想负责，可以AA和提供情绪价值，但不深入发展，每个都是暧昧的朋友\n试过社团聚餐等，没几个帅哥。我特别喜欢路上的肌肉男，直接上去要微信吗？下一步再约出来？但不想深交拉扯，只想亲嘴😭😭😭\n\n哥哥能传授一些现实社交的方法吗，感谢\n另外问问广大圈友有什么建议🙏\n（不喜欢酒吧和社交软件，喜欢学校里年轻强健的身体）",
    "content": "买个秒潮 比绝大多数♂人强",
    "domains": [
      "两性",
      "消费",
      "健康"
    ],
    "type": "方法论"
  },
  {
    "id": "processed_data_7-1605",
    "source_id": "1605",
    "date": "2024-09-06",
    "type_origin": "original_post",
    "source_question": "",
    "content": "来打鱼塘局当然自信了[呲牙]",
    "domains": [
      "情绪"
    ],
    "type": "事实陈述/推测预测"
  },
  {
    "id": "processed_data_7-1606",
    "source_id": "1606",
    "date": "2024-09-06",
    "type_origin": "original_post",
    "source_question": "",
    "content": "这世界上没有离了谁就不能转的，全世界光车祸每分钟就死两个人，就算一家饭店人死光了倒闭了，别人也不过换一家吃；今天谁在岗位上猝死了，明天就能再招一个；就是明星偶像死了，大家也不过就是换首歌听的事。至于没毕业的小登、失业的蹲子，那就更是烂命一条，有多少蹲蛆死了好几天闻到臭味才被发现的，除了死了能给清洁公司拉动内需，你死没死根本就没有区别，这世界真的不缺你一个，你不活有的是人活。",
    "domains": [
      "职业"
    ],
    "type": "方法论"
  },
  {
    "id": "processed_data_7-1607",
    "source_id": "1607",
    "date": "2024-09-05",
    "type_origin": "reply",
    "source_question": "请哥喝杯咖啡。配售性住房未来会实施吗？实施了会现在的市场产生什么影响吗？是不是买商品房就亏大了？",
    "content": "多读读文章 少胡思乱想 有好处[呲牙]",
    "domains": [
      "投资",
      "认知"
    ],
    "type": "方法论"
  },
  {
    "id": "processed_data_7-1608",
    "source_id": "1608",
    "date": "2024-09-05",
    "type_origin": "reply",
    "source_question": "男，ip海南，05年的\n因为高中在kk园区带不了手机不能看幻哥的课，后面听幻哥说可以直接拎包走人的时候已经没有多少天了，最后考的608(海南）(看不了课最后两个月开摆了）然后后面报志愿的时候还滑档了，只能报征集志愿，最后录到一个东百的二本机械\n三条路\n1回去复读，有幻哥的课加持，保底能考到海大的机械，211对后面考研有帮助，幻哥说以后机械会起飞，所以直接梭哈\n2就这个二本读下去，南方人到北方水土不服挺难受的，而且这学校的环境挺差的，又是滑档才上的更难受了，但是看星球里说卷学历已经废了，不知道该不该复读\n3复读后读护理润了，家里贫下中农，费用估计要自己搞",
    "content": "回去吧 不差这一两年的 \n尤其你还学机械的 又不是计算机挣青春饭",
    "domains": [
      "教育",
      "职业",
      "决策"
    ],
    "type": "方法论"
  },
  {
    "id": "processed_data_7-1609",
    "source_id": "1609",
    "date": "2024-09-05",
    "type_origin": "original_post",
    "source_question": "",
    "content": "又被大师兄血虐了[呲牙]",
    "domains": [
      "情绪"
    ],
    "type": "事实陈述/推测预测"
  },
  {
    "id": "processed_data_7-1610",
    "source_id": "1610",
    "date": "2024-09-05",
    "type_origin": "reply",
    "source_question": "幻幻，sjtu的junxun开始20：00～3：00的20km拉练了。。。",
    "content": "五年内安排高中作息 为祖国健康工作50年[呲牙]",
    "domains": [
      "健康",
      "教育",
      "职业"
    ],
    "type": "方法论"
  },
  {
    "id": "processed_data_7-1611",
    "source_id": "1611",
    "date": "2024-09-05",
    "type_origin": "reply",
    "source_question": "哥哥，本科就是个二本学院。目前在考研（会计专硕），水平也就能考个二本学院的研究生，和同学一说，被嘲讽了。学院的研究生值得去读吗😢",
    "content": "将就读吧 食之无味弃之可惜",
    "domains": [
      "教育",
      "决策",
      "职业"
    ],
    "type": "方法论"
  },
  {
    "id": "processed_data_7-1612",
    "source_id": "1612",
    "date": "2024-09-05",
    "type_origin": "reply",
    "source_question": "自己找工作自己实习有点想哭，而且陌生城市没朋友…哥哥骂我我也认了",
    "content": "忍忍就好了",
    "domains": [
      "职业",
      "人际",
      "情绪"
    ],
    "type": "思维方式"
  },
  {
    "id": "processed_data_7-1613",
    "source_id": "1613",
    "date": "2024-09-05",
    "type_origin": "reply",
    "source_question": "幻哥你真就一切尽在掌握呀，搞得我都想报你的政治课涨涨见识了。早上开会全方位提升黑爹以后的地位，下午中组部出台了限制高学历人才引进的规定，你为什么就能提前一年想到呢？",
    "content": "课里没有你想要的 就是讲题",
    "domains": [
      "教育"
    ],
    "type": "事实陈述/推测预测"
  },
  {
    "id": "processed_data_7-1614",
    "source_id": "1614",
    "date": "2024-09-05",
    "type_origin": "original_post",
    "source_question": "",
    "content": "有没有人知道这是为什么？怎么郭楠就天天挨斗了，不知道就找时间提一嘴[呲牙]",
    "domains": [
      "社会观察"
    ],
    "type": "事实陈述/推测预测"
  },
  {
    "id": "processed_data_7-1615",
    "source_id": "1615",
    "date": "2024-09-05",
    "type_origin": "original_post",
    "source_question": "",
    "content": "广阔天地准备在老师饭里下点料了[呲牙]",
    "domains": [
      "教育"
    ],
    "type": "事实陈述/推测预测"
  },
  {
    "id": "processed_data_7-1616",
    "source_id": "1616",
    "date": "2024-09-05",
    "type_origin": "original_post",
    "source_question": "",
    "content": "吴承恩是殖人，取关了[发怒]",
    "domains": [
      "内容创作"
    ],
    "type": "事实陈述/推测预测"
  },
  {
    "id": "processed_data_7-1617",
    "source_id": "1617",
    "date": "2024-09-05",
    "type_origin": "reply",
    "source_question": "刚毕业一年，目前做自媒体月入5k，但有一个问题：\n\n1.目前b端销售，工资1万，每天工作时间12小时，完全没有什么实际可以来发展副业。虽然工资高但感觉被限制死了\n\n目前有一个选择：快消饮料销售，比如伊利蒙牛，工资7、8千，但每天实际工作时间也就6个小时左右，有足够的时间寻找商业机会，发展副业。缺点在于这份工作上限很低，最多也就月入1万多\n\n我的问题是，我这样的策略有没有问题？\n\n通过找一份有闲但上限低的工作养活自己，然后不断地收取商业信息，发展副业。等副业发展起来了，就抛弃主业，all in副业？",
    "content": "如果你想挣很多钱 那一万和七八千其实没有区别\n但是时间很值钱",
    "domains": [
      "职业",
      "搞钱",
      "决策"
    ],
    "type": "思维方式"
  },
  {
    "id": "processed_data_7-1618",
    "source_id": "1618",
    "date": "2024-09-05",
    "type_origin": "reply",
    "source_question": "幻幻我是之前问这个，能不能细说一下？\n还有这个月接单好好的，有个屁事很多的顾客我就多收点了钱然后就给我个差评说我乱收费化的一般😭😭😭现在都没人找我了，已经开帖子写了回应，好像没什么变化，评价也举报不了，我是注销这个号重新开个新号还是咋整呀？（舍不得之前的好评）化妆是不是适合兼职做，不适合当主业\n本人对化妆比较感兴趣，但是好像这行比较卷，还有像我这种家里没钱没背景的女生的出路应该不适合润吧，应该如何找到适合自己的赛道，",
    "content": "说白了就是闲鱼流量太小的缘故 你需要更大的流量",
    "domains": [
      "搞钱",
      "职业",
      "决策"
    ],
    "type": "思维方式"
  },
  {
    "id": "processed_data_7-1619",
    "source_id": "1619",
    "date": "2024-09-05",
    "type_origin": "reply",
    "source_question": "卧槽我前ex是真煞笔啊，笑死我了我的真心都给狗吃了对吧，我是小丑🤡",
    "content": "你跟前一个帖子斗一下[呲牙]",
    "domains": [
      "两性",
      "人际",
      "情绪"
    ],
    "type": "事实陈述/推测预测"
  },
  {
    "id": "processed_data_7-1620",
    "source_id": "1620",
    "date": "2024-09-05",
    "type_origin": "reply",
    "source_question": "爹，我遇到的女人也是这样。在一起前都表现地非常喜欢我，对我也很好，在一起后我对她们温柔体贴，基本上三个月后就慢慢表现地自我，蛮横，对我越来越差。这是本性如此还是因为我表现地太龟了啊？",
    "content": "没有活学活用董志民思想[呲牙]",
    "domains": [
      "两性",
      "人际"
    ],
    "type": "事实陈述/推测预测"
  },
  {
    "id": "processed_data_7-1621",
    "source_id": "1621",
    "date": "2024-09-04",
    "type_origin": "original_post",
    "source_question": "",
    "content": "全方位无死角地好起来了[呲牙]",
    "domains": [
      "社会观察"
    ],
    "type": "思维方式"
  }
]
