[
  {
    "id": "processed_data_5-19",
    "source_id": "19",
    "date": "2024-12-30",
    "type_origin": "reply",
    "source_question": "幻大晚上好！我本科是双非一本，女生，英语专业，校招找到广东私立高中工作，一个月7千，工作不累，学生成绩非常差。\n家在黑龙江，想考黑龙江的公务员，但是在广东考黑龙江公务员不方便。\n干了半年，生病了。\n1.扁桃体有肿块，医生让我摘除扁桃体，这个手术可以做吗？\n现在两个选择\n1.假期回哈尔滨做手术，辞职，恢复期备考考公，之前省考事业编进面两次，但是都第二。\n2.不做手术，接着回私立学校备考。\n现在工作不好找，怕在家备考以后找工作困难，纠结回家备考还是接着在私立干",
    "content": "回去可没有这么轻松的工作了 开会写材料都烦死你\n先攒两年钱再说 一边自己琢磨考试 这么急干嘛",
    "domains": [
      "职业",
      "教育",
      "决策"
    ],
    "type": "方法论"
  },
  {
    "id": "processed_data_5-20",
    "source_id": "20",
    "date": "2024-12-30",
    "type_origin": "original_post",
    "source_question": "",
    "content": "🏦，崛起[发怒]",
    "domains": [
      "投资"
    ],
    "type": "事实陈述/推测预测"
  },
  {
    "id": "processed_data_5-21",
    "source_id": "21",
    "date": "2024-12-29",
    "type_origin": "reply",
    "source_question": "为什么有人喜欢霸凌别人，干这么无聊的事",
    "content": "错误的 有人的地方就有权力 霸凌说明这个班出现了权力真空 简单来说就是本来应该管事的老师不管事 所以自然会有人来管事 比如班霸校霸啥的\n霸凌只是确认我有权力能伤害你 如果你能打赢 那他就没有权力 如果你把他打进医院了 你就能霸凌别人",
    "domains": [
      "教育"
    ],
    "type": "思维方式"
  },
  {
    "id": "processed_data_5-22",
    "source_id": "22",
    "date": "2024-12-29",
    "type_origin": "reply",
    "source_question": "哥哥你好\n本人18 ip广东 985计算机大一 因为高考考差比平时少了30分左右（当初出分就想复读了，但父母逼着不给），再加上失利导致的恋爱分手，学校环境太烂\n这个学期基本都是郁郁寡欢，每天都过得好痛苦，因为没咋学基本每科都挂了，绩点应该是烂完了\n自媒体尝试搞了一下学习博主，但学历太低搞不起来没人看\n现在感觉看不到出路了，想过退学复读，但可能得考2026的高考\n哥哥能给本笨比一点建议吗谢谢哥哥",
    "content": "高考没必要了 太浪费时间了\n这个专业能力大于学历 何况你已经有学历了 不如想想看能不能做点项目提高一下能力 赚点钱\n\n也可以搞清楚到底是国内读还是出国\n国内的话看看支教当兵保研什么的能不能走\n如果出国 绩点也重要但权重就降低了 出国也不错",
    "domains": [
      "教育",
      "职业",
      "内容创作"
    ],
    "type": "方法论"
  },
  {
    "id": "processed_data_5-23",
    "source_id": "23",
    "date": "2024-12-29",
    "type_origin": "reply",
    "source_question": "幻，感觉一牵扯到人际关系，自己性格就比较懦弱，总是习惯牺牲自己来避免潜在的冲突。最近伤害到自己的核心利益了，痛定思痛，想改变性格，有什么建议嘛？",
    "content": "打不过就打不过 说这么多干嘛",
    "domains": [
      "人际",
      "决策",
      "情绪"
    ],
    "type": "方法论"
  },
  {
    "id": "processed_data_5-24",
    "source_id": "24",
    "date": "2024-12-29",
    "type_origin": "reply",
    "source_question": "割割问一下考研还是直接就业，211计算机专业大三女，嗯玩了两年0绩点0技术0实习,家底支持gap几年没钱留学\n不想考研的理由：\n1.计划找到机会就润（接受婚绿），在⏰苟活就行没想有发展，早点打工攒钱早点润\n2.不想再参与⏰卷人活动了（考研考编考公），能坐得住但是心里会纠结要不要卷\n3.计算机专业决定考研的话就要准备一整年天天都在嗯卷，毕业都29年了不知道贬值多少次了\n就业的话：\n1.这一年好好提升一下技术（学得进去但没很多天赋）+实习\n2.优先找外企和出海企业\n3.啃男人打工赚钱空闲时间做副业三合一苟活\n4.找不到工作，倒贴打工/打工累死了已老实再考研\n\n我知道考研和本科就业是两坨💩里面选一坨，我想早点有收入且打算润所以我目前倾向于先不考研，这个决策可能太局限太主观了，希望割割给我分析一下",
    "content": "p价高的时候，想办法卖高价自然是最好的路子，整别的都没用\n哥哥星球里早说过了 想办法勾搭已入美籍的清北姚班性压抑男程序员自然是最好的 给他下个崽 什么都给你办好了 更厉害的还能纯骗 钱和身份都有了 什么都不用付出\n这些人也是可怜人啊 别看国内人模狗样的 在🇺🇸是最底层的男人 出去🐞几百刀一次太贵了舍不得 都饿疯了 随便一头母猪他们都扑上去了\n整其他的都是凑合着过 卖高价才是主业[睡]",
    "domains": [
      "搞钱",
      "两性",
      "职业"
    ],
    "type": "方法论"
  },
  {
    "id": "processed_data_5-25",
    "source_id": "25",
    "date": "2024-12-29",
    "type_origin": "reply",
    "source_question": "幻哥我好犹豫啊，做自媒体博主是边学边做还是学得差不多了再发视频？心里很没底，想发视频但有时候我学到了更新的东西，就可能会推翻我之前说的理论，或者说之前说的那些也对但没踩中核心，怎么办？",
    "content": "咱们都是想发就发爱看不看 [睡]",
    "domains": [
      "内容创作"
    ],
    "type": "方法论"
  },
  {
    "id": "processed_data_5-26",
    "source_id": "26",
    "date": "2024-12-29",
    "type_origin": "reply",
    "source_question": "马航消失能不能说一嘴",
    "content": "就是掉海里找不到了呗 南海那么大 找得到个🐔巴",
    "domains": [
      "社会观察"
    ],
    "type": "事实陈述/推测预测"
  },
  {
    "id": "processed_data_5-27",
    "source_id": "27",
    "date": "2024-12-29",
    "type_origin": "original_post",
    "source_question": "",
    "content": "哥哥已经放救生艇了，没上船的只有[睡]",
    "domains": [
      "内容创作"
    ],
    "type": "事实陈述/推测预测"
  },
  {
    "id": "processed_data_5-28",
    "source_id": "28",
    "date": "2024-12-29",
    "type_origin": "original_post",
    "source_question": "",
    "content": "现在证明活着的只有俩乘务员 说白了就是坐机屁股那俩人\n听乘务员的待在机舱 全部都报销了\n但是照哥哥这套来操作 这把肯定是活了\n哥哥为什么要坐后排，说白了就是为了抢厕所，都是配套的[呲牙]",
    "domains": [
      "社会观察"
    ],
    "type": "思维方式"
  },
  {
    "id": "processed_data_5-29",
    "source_id": "29",
    "date": "2024-12-29",
    "type_origin": "original_post",
    "source_question": "",
    "content": "无药可救的东西[睡]",
    "domains": [
      "社会观察"
    ],
    "type": "思维方式"
  },
  {
    "id": "processed_data_5-31",
    "source_id": "31",
    "date": "2024-12-29",
    "type_origin": "original_post",
    "source_question": "",
    "content": "冷知识 空客的事故概率只有波音的5%[睡]",
    "domains": [
      "社会观察"
    ],
    "type": "事实陈述/推测预测"
  },
  {
    "id": "processed_data_5-32",
    "source_id": "32",
    "date": "2024-12-29",
    "type_origin": "original_post",
    "source_question": "",
    "content": "再教大家个狠的，哥哥早就琢磨明白了 \n一旦感觉到飞机💊 咱们就去抢厕所 \n进去就反锁，躲里面不出来，谁敲门都不理\n傻逼才去听乘务员的，抱头趴座位下面，一起报销\n在厕所里抱头蹲下，然后屁股朝着机头那边，最安全[呲牙]",
    "domains": [
      "社会观察"
    ],
    "type": "方法论"
  },
  {
    "id": "processed_data_5-33",
    "source_id": "33",
    "date": "2024-12-29",
    "type_origin": "original_post",
    "source_question": "",
    "content": "最新消息是只活了两个，哥哥一看就知道怎么回事\n肯定是坐后排的乘客和坐机屁股的空乘，其他的只能[睡]\n所以哥哥不理解那头等舱有什么好坐的，请哥哥免费坐都不坐[呲牙]",
    "domains": [
      "社会观察"
    ],
    "type": "事实陈述/推测预测"
  },
  {
    "id": "processed_data_5-34",
    "source_id": "34",
    "date": "2024-12-29",
    "type_origin": "reply",
    "source_question": "幻幻，这些比赛看着好像都挺没含金量",
    "content": "大学生真好骗[睡]",
    "domains": [
      "教育"
    ],
    "type": "思维方式"
  },
  {
    "id": "processed_data_5-35",
    "source_id": "35",
    "date": "2024-12-29",
    "type_origin": "original_post",
    "source_question": "",
    "content": "刚说呢 又摔飞机了 没➕星球就不这样[睡]",
    "domains": [
      "内容创作"
    ],
    "type": "事实陈述/推测预测"
  },
  {
    "id": "processed_data_5-36",
    "source_id": "36",
    "date": "2024-12-29",
    "type_origin": "reply",
    "source_question": "哥哥 我妈说口腔溃疡可以用小维C片放在上面 忍三天就好了 是他们以前budui的土方法 真的吗 一天我就受不了了",
    "content": "有用的",
    "domains": [
      "健康"
    ],
    "type": "事实陈述/推测预测"
  },
  {
    "id": "processed_data_5-37",
    "source_id": "37",
    "date": "2024-12-28",
    "type_origin": "original_post",
    "source_question": "",
    "content": "听说体制内不过紧日子了，还要加薪?[睡]",
    "domains": [
      "职业"
    ],
    "type": "事实陈述/推测预测"
  },
  {
    "id": "processed_data_5-38",
    "source_id": "38",
    "date": "2024-12-28",
    "type_origin": "reply",
    "source_question": "刚跟妈妈吵架，她反问我：怎么，你以为我的钱都是你的啊，想的美！（我不是她唯一的孩子，她跟前夫还有一个，她很愧疚）\n平时说什么不计付出不求回报甚至不用给她养老，生气了就变脸，开始跟我算账，怀疑我图她💰。\n这世上除了自己还能相信什么啊😧连普通家庭的妈妈都猜疑、恐吓自己的小孩。\n恐吓算不上吧，只能说越南的父母从来不乐意给小孩提供安全感和爱，喜欢利用小孩的不安言语暴力，“你不去上学，就xxx”“你不努力，就只配送外卖”……不是什么新鲜话题，但我还是想发出来。如果你看到这里了，那么谢谢你看到这里。",
    "content": "早说了 生你的目的是为了养老\n哥哥可能会有点区别 跟养猫养狗差不多 养着玩[呲牙]",
    "domains": [
      "人际",
      "价值观"
    ],
    "type": "思维方式"
  },
  {
    "id": "processed_data_5-39",
    "source_id": "39",
    "date": "2024-12-28",
    "type_origin": "original_post",
    "source_question": "",
    "content": "2026年微信全网阅读量第一文章:\n哎资本 哎房价 哎股价 哎批价，最后上升通道堵死，阶级固化彻底完成，年轻人彻底绝望[睡]",
    "domains": [
      "投资"
    ],
    "type": "方法论"
  }
]
