[
  {
    "id": "processed_data_7-1850",
    "source_id": "1850",
    "date": "2024-08-18",
    "type_origin": "original_post",
    "source_question": "",
    "content": "以前有个名人，在带着他老婆去别人家吃饭的时候，当着他老婆的面就说\n“对待女人就要像吃菜一样，不要老是只吃一样菜嘛，老吃一样菜就莫得味道了嘛，要多吃几样才不会腻嘛”\n结果给他老婆气的拍案而起，当场摔筷子走人了\n这就搞得请他来吃饭的夫妻二人非常尴尬，但是没有办法，他们俩还得硬着头皮给他打圆场\n而且他回家以后，他老婆也没让他跪搓衣板，也没写什么检讨书，啥事都没发生，简直爽歪歪啊\n哥哥看到这就立马崇拜上了，决定要向这位名人学习，以他为榜样\n关注幻幻，每天给大家带来一个毁三观的知识[呲牙]",
    "domains": [
      "两性",
      "内容创作",
      "学习"
    ],
    "type": "故事案例"
  },
  {
    "id": "processed_data_7-1851",
    "source_id": "1851",
    "date": "2024-08-18",
    "type_origin": "original_post",
    "source_question": "",
    "content": "昨天忘记说了，最近又收了个女儿 \n04年 163 78斤\n喜欢被羞辱sp窒息束缚强高\n无业，高中读了一半太累就不读了，做过擦边主播没做起来，陪酒太累不想去，天天在家躺尸被老太婆骂\n这种能处吗？[呲牙]",
    "domains": [
      "两性",
      "人际"
    ],
    "type": "事实陈述/推测预测"
  },
  {
    "id": "processed_data_7-1852",
    "source_id": "1852",
    "date": "2024-08-18",
    "type_origin": "reply",
    "source_question": "女，top2垃圾文科专业，目前大二，一直在做家教，现在在教培机构实习做运营➕一对一教学生，自认为英语教学能力很强，之后想all in英语教培➕当地升学指导，可以吗？（主要是其他工作也赚不到什么钱，自媒体目前也还没弄起来）求哥指点一下",
    "content": "暂时可以这么弄 长期来看还是要拓展方向\n可以从英语这个方向出发 也可以从top2这个身份出发",
    "domains": [
      "职业",
      "教育",
      "内容创作"
    ],
    "type": "方法论"
  },
  {
    "id": "processed_data_7-1853",
    "source_id": "1853",
    "date": "2024-08-18",
    "type_origin": "original_post",
    "source_question": "",
    "content": "还没赔呢？上次刷到我还在读大学[呲牙]",
    "domains": [
      "投资",
      "教育"
    ],
    "type": "事实陈述/推测预测"
  },
  {
    "id": "processed_data_7-1854",
    "source_id": "1854",
    "date": "2024-08-18",
    "type_origin": "reply",
    "source_question": "幻 对家人朋友态度不好特别凶 在外人面前又像一条狗一样 这种人的性格怎么形成的",
    "content": "这就是经典的⏰味啊，对自己人不好对外人好得不得了，是方方面面都有的\n隋朝还是唐朝的时候，有一次为了迎接外宾，其实就是中亚斯坦国的人和伊朗的波斯爹，长安城每一棵树上都挂着五彩斑斓的丝绸，每一条都贵的批爆，像不要钱一样挂在那\n但与此同时这些洋爹们都注意到了，怎么好多人衣不附体地在讨饭呢\n原因你再想想应该就明白了，咱就提示到这了[呲牙]",
    "domains": [
      "决策",
      "人际",
      "认知"
    ],
    "type": "方法论"
  },
  {
    "id": "processed_data_7-1855",
    "source_id": "1855",
    "date": "2024-08-18",
    "type_origin": "original_post",
    "source_question": "",
    "content": "花木兰?[呲牙]",
    "domains": [
      "内容创作"
    ],
    "type": "事实陈述/推测预测"
  },
  {
    "id": "processed_data_7-1856",
    "source_id": "1856",
    "date": "2024-08-18",
    "type_origin": "reply",
    "source_question": "1幻爹，教培这行还有前途吗，有没有必要彻底all in这行，\n2我是条已经毕业三年的二本🐶，觉得计算机太卷需要学的东西太多就去教培了，一直在教初中准备扩到高中教数学，到底是考研转行干别的好还是直接all in教培好点，给点建议吧幻爹",
    "content": "你也干不了别的啊 不信去考个公试试看",
    "domains": [
      "职业",
      "教育",
      "决策"
    ],
    "type": "方法论"
  },
  {
    "id": "processed_data_7-1857",
    "source_id": "1857",
    "date": "2024-08-18",
    "type_origin": "reply",
    "source_question": "幻大，如果和妹子过夜一般是带回家还是在酒店开房？带回家风险大而且后面有纠纷的话很难搞…",
    "content": "你真是纯种学渣啊 之前说这么多次一次都没记住呢[呲牙]",
    "domains": [
      "两性",
      "人际",
      "消费"
    ],
    "type": "事实陈述/推测预测"
  },
  {
    "id": "processed_data_7-1858",
    "source_id": "1858",
    "date": "2024-08-18",
    "type_origin": "reply",
    "source_question": "哥 厨男线下接触的时候总有反应咋搞 烦死了 好害怕被发现",
    "content": "你就直说你太可爱了 太喜欢你了",
    "domains": [
      "两性",
      "人际",
      "情绪"
    ],
    "type": "事实陈述/推测预测"
  },
  {
    "id": "processed_data_7-1859",
    "source_id": "1859",
    "date": "2024-08-18",
    "type_origin": "reply",
    "source_question": "幻，你觉得你被教育荼毒了吗",
    "content": "文化水平属于本科以下 看上去在问我 实际上在问你自己[呲牙]",
    "domains": [
      "教育",
      "认知"
    ],
    "type": "事实陈述/推测预测"
  },
  {
    "id": "processed_data_7-1860",
    "source_id": "1860",
    "date": "2024-08-18",
    "type_origin": "original_post",
    "source_question": "",
    "content": "前段时间有人不服气\n说我这辈子就不靠男的，我自己打工自己过，只要不饿死就行，孤独终老就完事了，实在不行还可以ghg，哼[傲慢]",
    "domains": [
      "两性",
      "搞钱",
      "职业"
    ],
    "type": "价值观"
  },
  {
    "id": "processed_data_7-1861",
    "source_id": "1861",
    "date": "2024-08-17",
    "type_origin": "reply",
    "source_question": "（这一版是原图，图片清晰点）\n幻哥，追问那个四大领域的那个，之前那个图片的简介确实不太清楚，这次把具体学习内容补充在图片上了\n\n坐标：香港科技大学广州，最终意愿也是在人工智能和大数据这两个二选一\n\n下图是两领域具体课程，左人工智能，右大数据，幻哥可以再过目看看不？如果感觉不好指路也可以放出来给圈子计算机相关友友看看，帮忙参考哪条出路好🙏🙏",
    "content": "我觉得深度学习 机器学习 神经网络三个是必须学的吧 \n人工智能这个属于往里面掺水了 但是三个里面也有两个了 如果你是学弱，又想从事人工智能相关行业，那就将就学吧 有空补上 反正计算机本来也是自学",
    "domains": [
      "学习",
      "职业",
      "教育"
    ],
    "type": "方法论"
  },
  {
    "id": "processed_data_7-1862",
    "source_id": "1862",
    "date": "2024-08-17",
    "type_origin": "original_post",
    "source_question": "",
    "content": "这不是之前那个准大专生 她被控制欲超强的变态老妈喊回家不让出门了\n这是前段时间新收的 不要搞混了[呲牙]",
    "domains": [
      "教育",
      "人际"
    ],
    "type": "事实陈述/推测预测"
  },
  {
    "id": "processed_data_7-1863",
    "source_id": "1863",
    "date": "2024-08-17",
    "type_origin": "original_post",
    "source_question": "",
    "content": "回国吧要不[发怒]",
    "domains": [
      "决策"
    ],
    "type": "事实陈述/推测预测"
  },
  {
    "id": "processed_data_7-1864",
    "source_id": "1864",
    "date": "2024-08-17",
    "type_origin": "reply",
    "source_question": "幻哥，之前21年你大饼看的很准 这一轮大饼还有戏吗？ 是按照周期明年年底跑 ，还是现在就已经是断头饭了 抓紧跑路 望幻哥指点迷津(˵¯͒〰¯͒˵) A7.6",
    "content": "恁妈个逼 白嫖?[发怒]",
    "domains": [
      "投资"
    ],
    "type": "事实陈述/推测预测"
  },
  {
    "id": "processed_data_7-1865",
    "source_id": "1865",
    "date": "2024-08-17",
    "type_origin": "original_post",
    "source_question": "",
    "content": "应该是造谣了[呲牙]",
    "domains": [
      "社会观察"
    ],
    "type": "事实陈述/推测预测"
  },
  {
    "id": "processed_data_7-1866",
    "source_id": "1866",
    "date": "2024-08-17",
    "type_origin": "reply",
    "source_question": "嬛嬛帮我发出来吧，谢谢爹\n真的想死，家里让我帮忙贷款\n我22，贷款20w，利息8w，一个月还7200\n现在又让我填补一个95w的大窟窿。\n做法：让我假装是购房者买自家房去贷款120w，先把之前房屋抵押贷款没还上的95w还上，目前正在进行中不知道额度能不能下来，预计还30年一个月5000多。\n—但我同时还有一个50w的共同还款人，一个月1000多，签字是和我妈一起还款。\n（我爸已经征信黑了）\n\n开学我就要去厦门上研究生，艺术学专业，不挣钱。\n这个房屋贷款一共要还30年，家里人说的是一切先紧着我的还，（我肯定不信）\n但是我们一个月还款就是各种负债，还有信用卡什么的要还5w\n我妈带着十岁的弟弟不挣钱在家里蹲\n我爹创业抖音，偶尔能一个月入十万，但是开公司成本五万，有的时候发完工资他一万都没\n这就是为什么我要紧急贷款20w，填补窟窿\n补充：\n坐标郑州\n郊区这套房子成本200w，购房100，装修100\n（装修100是真傻逼）\n市区买的时候140w，也是抵押，160w，明年三月到期\n一个奔驰卖了，一个宝马快还完\n问题：\n签不签这个贷款？\n\n我如果不签字的话，一个月高息的20w的这个还款，7200，我还不起\n我如果签字的话，可能大概率就是我自己还\n但是后路可能是可以把房子卖掉，目前贝壳上预估的是能卖120w，到时候找过桥走一下卖一下。",
    "content": "什么玩意 借这么多钱干嘛 别把自己往死里逼啊",
    "domains": [
      "决策",
      "教育",
      "搞钱"
    ],
    "type": "方法论"
  },
  {
    "id": "processed_data_7-1867",
    "source_id": "1867",
    "date": "2024-08-17",
    "type_origin": "reply",
    "source_question": "幻哥，想问问这四个领域哪个未来更有搞头\n（25年入学，读2年制的研究生）",
    "content": "把人工智能去掉 太虚了吧 学的什么🐶💩 挂羊头卖狗肉呢\n剩下的看个人了 比如你喜欢动漫游戏就媒体艺术 喜欢工科男那种氛围就物联网 纯码农就大数据\n不过我觉得还是物联网或者媒体艺术实在一点",
    "domains": [
      "学习",
      "职业",
      "教育"
    ],
    "type": "方法论"
  },
  {
    "id": "processed_data_7-1868",
    "source_id": "1868",
    "date": "2024-08-17",
    "type_origin": "reply",
    "source_question": "哥哥 梅西事件回旋镖了 好像是主办方业余还一直逼着人家 港也在⏰的范围里吗 主办方居然是个杂志社 立本人家就专业多了",
    "content": "之前说过了 本质上是阶级落差学\n港🐒虽然在⏰人圈子里面可以当上等人，但是在小黄人这个圈子里，离日本新加坡差得远呢[呲牙]",
    "domains": [
      "教育",
      "认知"
    ],
    "type": "思维方式"
  },
  {
    "id": "processed_data_7-1869",
    "source_id": "1869",
    "date": "2024-08-17",
    "type_origin": "original_post",
    "source_question": "",
    "content": "哎，她被发配到一个司马民办大专了 \n一个学期要踏马一万块学费 还在郊区 还学市场营销\n关键是学校和高中完全一样，天天晚自习\n周末放一天半，周天下午回来上晚自习\n这可怎么办啊？[流泪]",
    "domains": [
      "教育",
      "情绪"
    ],
    "type": "事实陈述/推测预测"
  }
]
