[
  {
    "id": "processed_data_2-499",
    "source_id": "499",
    "date": "2025-08-29",
    "type_origin": "original_post",
    "source_question": "",
    "content": "现在➕星球，跟上节奏\n那就还有点希望，毕竟单位里的比较好撸贷款\n晚了只能洗洗睡了[呲牙]",
    "domains": [
      "搞钱",
      "投资",
      "内容创作"
    ],
    "type": "事实陈述/推测预测"
  },
  {
    "id": "processed_data_2-500",
    "source_id": "500",
    "date": "2025-08-28",
    "type_origin": "reply",
    "source_question": "发现章泽天和武大那个女的面相好像🤔",
    "content": "盲僧?\n\n---\n\n# hymy - 第13批\n\n**共 100 条内容**\n\n**导出时间**: 2025-12-06 14:09:10",
    "domains": [
      "社会观察"
    ],
    "type": "事实陈述/推测预测"
  },
  {
    "id": "processed_data_2-501",
    "source_id": "501",
    "date": "2025-08-28",
    "type_origin": "reply",
    "source_question": "昨天那女的骑坐在我腰上好像蹭到门口了，今天顺路去最近的社区卫生中心，告诉我查不了淋疣，查梅艾要5天，想72小时抢救找疾控中心。爱咋咋地吧。我插绝对带保护的，这要能中，那拿手摸拿嘴舔也能中，这概率没那么大吧？还是说我命不久矣只剩8年🙀",
    "content": "用星球里那个🐶85的话 你有点杞人忧天了[呲牙]",
    "domains": [
      "健康",
      "内容创作"
    ],
    "type": "事实陈述/推测预测"
  },
  {
    "id": "processed_data_2-502",
    "source_id": "502",
    "date": "2025-08-28",
    "type_origin": "original_post",
    "source_question": "",
    "content": "梭吧 不要委屈自己了\n人就活这么一回 梭了就没有遗憾了 赚钱赔钱有那么重要吗？[呲牙]",
    "domains": [
      "投资",
      "搞钱"
    ],
    "type": "价值观"
  },
  {
    "id": "processed_data_2-503",
    "source_id": "503",
    "date": "2025-08-28",
    "type_origin": "original_post",
    "source_question": "",
    "content": "我看了那个白冰的减肥方法\n什么吃🐔胸肉，然后使劲锻炼\n看到这我就觉得他在扯淡了，要么就是太难了，要么就是他在编蛆搞节目效果，实际上靠司美\n反正哥哥是没这个毅力的，鸡胸肉那么难吃🐶都不吃好吧，而且7月那会我掉最快的时候，动都不想动，一样掉，没必要那么辛苦[呲牙]",
    "domains": [
      "健康",
      "价值观"
    ],
    "type": "价值观"
  },
  {
    "id": "processed_data_2-504",
    "source_id": "504",
    "date": "2025-08-28",
    "type_origin": "original_post",
    "source_question": "",
    "content": "听说谈判内容是人仔大幅升值? \n如果是真的，那大大大的要来了[惊恐]",
    "domains": [
      "投资"
    ],
    "type": "事实陈述/推测预测"
  },
  {
    "id": "processed_data_2-505",
    "source_id": "505",
    "date": "2025-08-28",
    "type_origin": "original_post",
    "source_question": "",
    "content": "DAY69：我发现我错了\n其实还是有在降的，就是比较慢而已，现在一称又新低了\n如果全力以赴去减，可以做到一天一斤\n现在半摆烂地搞，可能一天二两吧，只要别嘴贱去喝奶茶就行了，之前没掉是因为喝霸王茶姬去了[尴尬]",
    "domains": [
      "健康"
    ],
    "type": "事实陈述/推测预测"
  },
  {
    "id": "processed_data_2-506",
    "source_id": "506",
    "date": "2025-08-28",
    "type_origin": "original_post",
    "source_question": "",
    "content": "射完以后睡着了，一觉醒来发现突然就阳痿了，对股市没兴趣了\n以后尽量不谈这破玩意了，爱咋咋地吧，以后找点别的事情干一干[睡]",
    "domains": [
      "投资"
    ],
    "type": "价值观"
  },
  {
    "id": "processed_data_2-507",
    "source_id": "507",
    "date": "2025-08-28",
    "type_origin": "reply",
    "source_question": "年轻人迷茫不知道干点啥工作，幻哥说学技术也坚持不下来怎么办，干什么工作都喜欢跑路😅",
    "content": "那说明你家老头👵还在源源不断地给你爆金币\n所以你还在这里装逼，你还没有到饿到偷士力架的程度\n你可以转型爆金币路线 没开玩笑[呲牙]",
    "domains": [
      "职业",
      "搞钱"
    ],
    "type": "事实陈述/推测预测"
  },
  {
    "id": "processed_data_2-509",
    "source_id": "509",
    "date": "2025-08-28",
    "type_origin": "original_post",
    "source_question": "",
    "content": "哥哥也是这么想的\n这垃圾东西，继续拿着只会彻底输麻[发怒]\n我已经全卖了，你们这些傻子继续在里面套着吧哈哈哈[呲牙]",
    "domains": [
      "投资"
    ],
    "type": "事实陈述/推测预测"
  },
  {
    "id": "processed_data_2-510",
    "source_id": "510",
    "date": "2025-08-28",
    "type_origin": "reply",
    "source_question": "哥哥 大学不是建议学电焊嘛",
    "content": "不要嘴炮 你去试试啊",
    "domains": [
      "教育",
      "职业",
      "决策"
    ],
    "type": "方法论"
  },
  {
    "id": "processed_data_2-511",
    "source_id": "511",
    "date": "2025-08-27",
    "type_origin": "reply",
    "source_question": "寰寰，马上要开学了，大一新生应该做什么才能赢在起跑线",
    "content": "找家里面爆点钱 连哄带骗的\n然后在学校里学校外各种做生意 能⭕️一点是一点\n除非理工科学的进去，或者你确定要考公考研保研，不然最好都这样[呲牙]",
    "domains": [
      "教育",
      "搞钱",
      "职业"
    ],
    "type": "方法论"
  },
  {
    "id": "processed_data_2-512",
    "source_id": "512",
    "date": "2025-08-27",
    "type_origin": "reply",
    "source_question": "幻哥，问个口腔问题（懂的圈友也可以回答一下，谢谢）\n你觉得最正确的刷牙方法，和好的牙膏是什么，以及平时该如何才能最大程度保护牙齿",
    "content": "从来没想过 就正常刷呗",
    "domains": [
      "健康"
    ],
    "type": "价值观"
  },
  {
    "id": "processed_data_2-513",
    "source_id": "513",
    "date": "2025-08-27",
    "type_origin": "reply",
    "source_question": "幻幻你的精神支柱是啥",
    "content": "我没有 过一天算一天",
    "domains": [
      "情绪"
    ],
    "type": "价值观"
  },
  {
    "id": "processed_data_2-514",
    "source_id": "514",
    "date": "2025-08-27",
    "type_origin": "original_post",
    "source_question": "",
    "content": "以后我的小逼仔就这样，你们不是要过来投胎吗？我看谁敢[呲牙]",
    "domains": [
      "教育"
    ],
    "type": "价值观"
  },
  {
    "id": "processed_data_2-515",
    "source_id": "515",
    "date": "2025-08-27",
    "type_origin": "original_post",
    "source_question": "",
    "content": "随便一个傻逼女人，房子这一块的认知都吊打知乎高学历屌丝男，这是基因决定的[呲牙]",
    "domains": [
      "两性",
      "认知"
    ],
    "type": "思维方式"
  },
  {
    "id": "processed_data_2-516",
    "source_id": "516",
    "date": "2025-08-27",
    "type_origin": "original_post",
    "source_question": "",
    "content": "最高点3887 你3885梭了\n美股哥嘴硬装死了，你现在是星球最宝贵的人才了\n就你这样的，记得年年续费，不续费你得死[呲牙]",
    "domains": [
      "投资",
      "内容创作"
    ],
    "type": "事实陈述/推测预测"
  },
  {
    "id": "processed_data_2-517",
    "source_id": "517",
    "date": "2025-08-27",
    "type_origin": "reply",
    "source_question": "幻哥，平时深蹲或者练腿后，怎么放松啊，第二天起来腿会感到很酸",
    "content": "那说明你频率太低了 如果天天蹲 前几天会疼 那时候休息 后面恢复了啥事没有",
    "domains": [
      "健康"
    ],
    "type": "方法论"
  },
  {
    "id": "processed_data_2-518",
    "source_id": "518",
    "date": "2025-08-27",
    "type_origin": "original_post",
    "source_question": "",
    "content": "你梭的时候通知一声行不行[发怒]",
    "domains": [
      "投资"
    ],
    "type": "事实陈述/推测预测"
  },
  {
    "id": "processed_data_2-519",
    "source_id": "519",
    "date": "2025-08-27",
    "type_origin": "original_post",
    "source_question": "",
    "content": "这个月搞了七八十次了，现在真的彻底虚了 \n硬度和时间都下降了，当然这也和哥哥懒了有关系\n尤其是硬度，今天开始居然做一半软了\n哎男人累，哥哥都这样了，那些结了婚不锻炼的男人只会更惨\n男人就没办法，女人可以躺平，男人只能奋斗[流泪]\n所以哥哥不得不重新原神启动了，外加深蹲这些，必须找回场子[发怒]",
    "domains": [
      "两性",
      "健康",
      "情绪"
    ],
    "type": "事实陈述/推测预测"
  }
]
