[
  {
    "id": "processed_data_9-9",
    "source_id": "9",
    "date": "2023-12-30",
    "type_origin": "original_post",
    "source_question": "",
    "content": "为了骗大学生钱 \n还是要把幻夜梦屿这个公众号拿到自己手上 哎太穷了现在 要做点没底线的事情了[呲牙]",
    "domains": [
      "内容创作",
      "搞钱",
      "教育"
    ],
    "type": "事实陈述/推测预测"
  },
  {
    "id": "processed_data_9-10",
    "source_id": "10",
    "date": "2023-12-30",
    "type_origin": "reply",
    "source_question": "幻哥，\n技术是真太吃香了😭😭\n我家那三四线小城市，一个主要做纹眉的个人工作室，日入6k➕\n当然店主本人在这一行干了快10年了，效果确实很好",
    "content": "中国人还是有钱的 唱响中国经济光明论[呲牙]",
    "domains": [
      "职业"
    ],
    "type": "事实陈述/推测预测"
  },
  {
    "id": "processed_data_9-11",
    "source_id": "11",
    "date": "2023-12-30",
    "type_origin": "reply",
    "source_question": "幻幻，我现在211大一，从中考完就关注你，从知乎追到b站再到知识星球，非常感谢你的分享。\n 这学期靠自己摸索，十一月在小红书搞了一个纯图文的高三艺考生的学习账号，基本就是发布分享心态调整和学习方法的文章，一个月涨粉了1700，十二月之后懒了没更新了，流量还少了很多😭\n 到现在只变现一百块，求指点之后怎么做，必须转型，在想要不要引流公众号做付费文章/开抖b做视频，以及是否需要从纯文章转到图文，预留广告位(这样流量肯定会打折)。",
    "content": "你又不给钱 关我啥事[呲牙]",
    "domains": [
      "人际",
      "内容创作",
      "学习"
    ],
    "type": "方法论"
  },
  {
    "id": "processed_data_9-12",
    "source_id": "12",
    "date": "2023-12-30",
    "type_origin": "original_post",
    "source_question": "",
    "content": "我好同学想来也上了三年班了，这回不会倒下了吧？[呲牙]",
    "domains": [
      "职业"
    ],
    "type": "事实陈述/推测预测"
  },
  {
    "id": "processed_data_9-13",
    "source_id": "13",
    "date": "2023-12-30",
    "type_origin": "original_post",
    "source_question": "",
    "content": "真的越来越幸福了[呲牙]",
    "domains": [
      "情绪"
    ],
    "type": "事实陈述/推测预测"
  },
  {
    "id": "processed_data_9-14",
    "source_id": "14",
    "date": "2023-12-30",
    "type_origin": "reply",
    "source_question": "哥 你觉得吃东西的口味跟xing压抑有关系吗？",
    "content": "广东人口味挺清淡的 也不妨碍广东是避孕套卖的最多的地方\n重庆成都吃的辣 妖魔鬼怪一样那么多 所以没什么关系",
    "domains": [
      "两性"
    ],
    "type": "事实陈述/推测预测"
  },
  {
    "id": "processed_data_9-15",
    "source_id": "15",
    "date": "2023-12-30",
    "type_origin": "reply",
    "source_question": "哥，买企业级店铺衣服鞋子时候怎么分辨店铺的东西质量好坏？买了再退货这种感觉有点麻烦",
    "content": "这需要试错 要靠熟人推荐",
    "domains": [
      "消费"
    ],
    "type": "方法论"
  },
  {
    "id": "processed_data_9-16",
    "source_id": "16",
    "date": "2023-12-30",
    "type_origin": "original_post",
    "source_question": "",
    "content": "哥哥早说了，这种人不会有好下场的[呲牙]",
    "domains": [
      "社会观察"
    ],
    "type": "事实陈述/推测预测"
  },
  {
    "id": "processed_data_9-18",
    "source_id": "18",
    "date": "2023-12-29",
    "type_origin": "original_post",
    "source_question": "",
    "content": "他🐎的 现在这优衣库越来越贵了 真不如买企业级了\n我决定了 2024年要穿一年的企业级 咱也体验一下上面LV下面Gucci的感觉[呲牙]",
    "domains": [
      "消费"
    ],
    "type": "事实陈述/推测预测"
  },
  {
    "id": "processed_data_9-19",
    "source_id": "19",
    "date": "2023-12-29",
    "type_origin": "reply",
    "source_question": "幻 破案了 对方是个海王 \n今天他吃饭的时候无意间跟他聊了几句 他说谈恋爱就是因为要做爱啊 他说之前有一个女的15太小了没做成功 不是男女朋友还是人家倒贴过来的 然后问了他是不是女生贴上来都不拒绝 他说那要看长的好不好看 还说出去泡妞都要找好看的\n我去 幻 破防了 原来所谓深情人设都是假的 \n他还说他不让别人碰她女朋友的 不然就不要她了 这咋搞啊",
    "content": "人家长的帅的凭什么要深情啊 不多艹几个比那不脑残吗？ \n想找又帅又深情的去看小说啊[呲牙]",
    "domains": [
      "两性",
      "人际"
    ],
    "type": "价值观"
  },
  {
    "id": "processed_data_9-20",
    "source_id": "20",
    "date": "2023-12-29",
    "type_origin": "reply",
    "source_question": "幻幻，我家里的一位长辈(70年代生人)即使赚了很多钱(a9，传统建筑行业)，也依然认为只有读了研究生才是人上人，才能赚到大钱(他对我说的原话是“我们长辈虽然能力不及有些年轻人，但我们对社会的看法是更客观更长远的，学历代表的是一个背景，没有背景的人是达不到大富大贵的”)，\n\n他很坚持让我去读研，他甚至觉得我哪怕去读个双非二本的研究生都是人上人(这与幻幻“能不能挣到钱跟学历没啥关系”这一观点并不重合)。\n\n出于对长辈的尊敬以及培养感情的目的，我没有反驳他的观点，只能表示认同。甚至我想过，以后如果是为了分他的财产，我需要不得不顺从他的想法去读个研。\n\n幻幻认为他有这种想法是什么原因？(我的的猜测是，这可能与他所在的生态位有关，他那个位置看到的比他强的强者，都是高学历，所以会觉得研究生都是人上人)",
    "content": "他成长的年代是八九十年代 那时候大学生是有用的 所以他看到的就都是谁谁谁读了大学就逆袭了翻身了吃上国家粮了 再也不用当农逼了\n而他学历很低 很自卑 当年就是因为学历太低才跑去干建筑的 结果没想到妈的发财了 这完全是意料之外的事情 \n要是按照70年代或者更早的版本 他本来的命运就是最底层的贱民 要在村里种一辈子地然后撑死 是因为非常侥幸地赶上了好时代才改变了命运\n所以那种年轻时的自卑依然是他一生挥之不去的阴影，得不到的就越想要，他自然就会疯狂给你洗脑了[呲牙]",
    "domains": [
      "教育",
      "认知"
    ],
    "type": "方法论"
  },
  {
    "id": "processed_data_9-21",
    "source_id": "21",
    "date": "2023-12-29",
    "type_origin": "original_post",
    "source_question": "",
    "content": "哪里人在呼吸香甜空气呢[呲牙]",
    "domains": [
      "社会观察"
    ],
    "type": "事实陈述/推测预测"
  },
  {
    "id": "processed_data_9-22",
    "source_id": "22",
    "date": "2023-12-29",
    "type_origin": "reply",
    "source_question": "幻哥，我每天大量的时间都花在看手机上了，虽说之前也是因为这个原因在自媒体这一块赚了六位数，但是这样确实不大健康，每天眼睛都挺累的，精神状态时好时坏，不大懂得休息是这样的。有什么好的替代方法或者参考经验吗",
    "content": "你去看张大仙 整个人都憔悴完了还要在那直播 钱也没少挣啊 没办法太挣钱了 你去做别的根本没有这么挣钱\n做这行除非你钱挣够不干了 或者像我一样是细分领域的 和热点关系不大\n不然免不了这样的 一天脱离网络你都很可能失去网感",
    "domains": [
      "内容创作",
      "职业",
      "搞钱"
    ],
    "type": "方法论"
  },
  {
    "id": "processed_data_9-23",
    "source_id": "23",
    "date": "2023-12-29",
    "type_origin": "reply",
    "source_question": "下学期开学就军训了，求教幻大，有什么有效的逃训路子？",
    "content": "我觉得最好还是假如宣传部 写写公众号拍拍照",
    "domains": [
      "教育",
      "内容创作"
    ],
    "type": "方法论"
  },
  {
    "id": "processed_data_9-24",
    "source_id": "24",
    "date": "2023-12-29",
    "type_origin": "original_post",
    "source_question": "",
    "content": "川🐭滚出来挨打[呲牙]",
    "domains": [
      "情绪"
    ],
    "type": "事实陈述/推测预测"
  },
  {
    "id": "processed_data_9-25",
    "source_id": "25",
    "date": "2023-12-29",
    "type_origin": "original_post",
    "source_question": "",
    "content": "梦见老子去人大附中 被那些人疯狂屠杀\n更气的是我同桌也在人大附中，考进了最好的办法\n哎高考你妈逼，毁我青春啊[发怒]",
    "domains": [
      "教育",
      "情绪"
    ],
    "type": "事实陈述/推测预测"
  },
  {
    "id": "processed_data_9-27",
    "source_id": "27",
    "date": "2023-12-29",
    "type_origin": "original_post",
    "source_question": "",
    "content": "听说越闹越大了 以后就来点什么事就炸 不知道哪一天幸福就启动了",
    "domains": [
      "社会观察"
    ],
    "type": "事实陈述/推测预测"
  },
  {
    "id": "processed_data_9-28",
    "source_id": "28",
    "date": "2023-12-28",
    "type_origin": "original_post",
    "source_question": "",
    "content": "接下来两年\n是赶英超美的两年，也是财富再一次剧烈分化的两年\n前面几年一直在好好耕耘，做好准备了的就会暴富\n整天在知乎上阴阳怪气的到时候又要拍断大腿，又要焦虑没赶上了，又开始哎资本了，反正剧本就是这么个剧本[呲牙]",
    "domains": [
      "搞钱",
      "投资",
      "情绪"
    ],
    "type": "方法论"
  },
  {
    "id": "processed_data_9-29",
    "source_id": "29",
    "date": "2023-12-28",
    "type_origin": "reply",
    "source_question": "幻大还会玩lol吗？",
    "content": "会下棋",
    "domains": [
      "认知"
    ],
    "type": "事实陈述/推测预测"
  },
  {
    "id": "processed_data_9-30",
    "source_id": "30",
    "date": "2023-12-28",
    "type_origin": "reply",
    "source_question": "幻哥喜欢成都嘛，为什么不在成都呆一段时间呢",
    "content": "还可以 但是冬天太冷有雾霾 每天都黑压压的看不到太阳 夏天太热 \n这是不好的地方",
    "domains": [
      "社会观察"
    ],
    "type": "事实陈述/推测预测"
  }
]
